README.rst
setup.cfg
setup.py
pyraven.egg-info/PKG-INFO
pyraven.egg-info/SOURCES.txt
pyraven.egg-info/dependency_links.txt
pyraven.egg-info/entry_points.txt
pyraven.egg-info/requires.txt
pyraven.egg-info/top_level.txt
raven/__init__.py
raven/_version.py
raven/raven.py
raven/tests/__init__.py
raven/tests/test_utils.py