Metadata-Version: 1.1
Name: pyraven
Version: 0.1.5
Summary: Interface with the Rainforest Automation RAVEn USB stick
Home-page: https://github.com/nonspecialist/pyraven
Author: Colin Panisset
Author-email: github@clabber.com
License: GPLv3
Keywords: usb energy raven smart meter
Platform: UNKNOWN
Classifier: Development Status :: 3 - Alpha
Classifier: Intended Audience :: Developers
Classifier: Intended Audience :: System Administrators
Classifier: License :: OSI Approved :: GNU General Public License v3 (GPLv3)
Classifier: Programming Language :: Python :: 2
Classifier: Programming Language :: Python :: 2.7
Classifier: Programming Language :: Python :: 3
Classifier: Programming Language :: Python :: 3.5
Classifier: Programming Language :: Python :: 3.6
Classifier: Topic :: Home Automation
